{"networkName": "Textile_1", "networkID": 52, "networkMeta": {"openStatistics": null, "openTest": null, "zoom": 1, "netMode": "edit", "coreStatus": {"Status": "Waiting"}, "chartsRequest": {"timerID": null, "waitGlobalEvent": false, "doRequest": 0, "showCharts": 0}}, "networkElementList": {"1599466463769": {"layerId": "1599466463769", "copyId": null, "copyContainerElement": null, "layerName": "Data_1", "layerType": "Data", "layerSettings": {"Type": "Data", "testInfoIsInput": true, "accessProperties": {"Columns": [], "Dataset_size": "", "Category": "Local", "Type": "Data", "Sources": [{"type": "file", "path": "C:/Users/ARUNESH/Anaconda3/envs/spring/Lib/site-packages/perceptilabs/tutorial_data/X_textile.npy"}], "PathFake": [], "Partition_list": [[70, 20, 10]], "Shuffle_data": true, "Action_space": ""}}, "layerSettingsTabName": "Computer", "layerCode": null, "layerCodeError": null, "layerNone": false, "layerMeta": {"isInvisible": false, "isLock": false, "isSelected": true, "position": {"top": 15, "left": 15}, "OutputDim": "64x64", "InputDim": "[]", "layerContainerName": "", "layerBgColor": "", "containerDiff": {"top": 0, "left": 0}}, "chartData": {}, "checkpoint": [], "endPoints": [], "componentName": "DataData", "connectionOut": [], "connectionIn": [], "connectionArrow": [], "visited": true, "inputs": {}, "outputs": {"15994664637690": {"name": "output", "reference_var": "output"}}, "forward_connections": [{"src_var": "output", "dst_id": "1599466525877", "dst_var": "input"}], "backward_connections": [], "previewVariable": "output", "previewVariableList": []}, "1599466475239": {"layerId": "1599466475239", "copyId": null, "copyContainerElement": null, "layerName": "Data_2", "layerType": "Data", "layerSettings": {"Type": "Data", "testInfoIsInput": true, "accessProperties": {"Columns": [], "Dataset_size": "", "Category": "Local", "Type": "Data", "Sources": [{"type": "file", "path": "C:/Users/ARUNESH/Anaconda3/envs/spring/Lib/site-packages/perceptilabs/tutorial_data/Y_textile.npy"}], "PathFake": [], "Partition_list": [[70, 20, 10]], "Shuffle_data": true, "Action_space": ""}}, "layerSettingsTabName": "Computer", "layerCode": null, "layerCodeError": null, "layerNone": false, "layerMeta": {"isInvisible": false, "isLock": false, "isSelected": false, "position": {"top": 340, "left": 20}, "OutputDim": "1", "InputDim": "[]", "layerContainerName": "", "layerBgColor": "", "containerDiff": {"top": 0, "left": 0}}, "chartData": {}, "checkpoint": [], "endPoints": [], "componentName": "DataData", "connectionOut": [], "connectionIn": [], "connectionArrow": [], "visited": true, "inputs": {}, "outputs": {"15994664752390": {"name": "output", "reference_var": "output"}}, "forward_connections": [{"src_var": "output", "dst_id": "1599467145388", "dst_var": "input"}], "backward_connections": [], "previewVariable": "output", "previewVariableList": []}, "1599466492197": {"layerId": "1599466492197", "copyId": null, "copyContainerElement": null, "layerName": "Convolution_1", "layerType": "Other", "layerSettings": {"Conv_dim": "2D", "Patch_size": "3", "Stride": "2", "Padding": "SAME", "Feature_maps": "64", "Activation_function": "ReLU", "Dropout": false, "Keep_prob": "1", "Batch_norm": true, "PoolBool": false, "Pooling": "Max", "Pool_area": "2", "Pool_padding": "SAME", "Pool_stride": "2"}, "layerSettingsTabName": "Settings", "layerCode": null, "layerCodeError": null, "layerNone": false, "layerMeta": {"isInvisible": false, "isLock": false, "isSelected": false, "position": {"top": 15, "left": 255}, "OutputDim": "32x32x64", "InputDim": "[64, 64, 1]", "layerContainerName": "", "layerBgColor": "", "containerDiff": {"top": 0, "left": 0}}, "chartData": {}, "checkpoint": [], "endPoints": [], "componentName": "DeepLearningConv", "connectionOut": [], "connectionIn": [], "connectionArrow": [], "visited": true, "inputs": {"15994664921970": {"name": "input", "reference_var_id": "15994665258780", "reference_layer_id": "1599466525877", "isDefault": true}}, "outputs": {"15994664921970": {"name": "output", "reference_var": "output"}}, "forward_connections": [{"src_var": "output", "dst_id": "1599466570500", "dst_var": "input"}, {"src_var": "output", "dst_id": "1599466592651", "dst_var": "input1"}], "backward_connections": [{"src_id": "1599466525877", "src_var": "output", "dst_var": "input"}], "previewVariable": "output", "previewVariableList": []}, "1599466525877": {"layerId": "1599466525877", "copyId": null, "copyContainerElement": null, "layerName": "Reshape_1", "layerType": "Other", "layerSettings": {"Shape": [64, 64, 1], "Permutation": [0, 1, 2]}, "layerSettingsTabName": "Settings", "layerCode": null, "layerCodeError": null, "layerNone": false, "layerMeta": {"isInvisible": false, "isLock": false, "isSelected": false, "position": {"top": 15, "left": 135}, "OutputDim": "64x64x1", "InputDim": "[64, 64]", "layerContainerName": "", "layerBgColor": "", "containerDiff": {"top": 0, "left": 0}}, "chartData": {}, "checkpoint": [], "endPoints": [], "componentName": "ProcessReshape", "connectionOut": [], "connectionIn": [], "connectionArrow": [], "visited": true, "inputs": {"15994665258780": {"name": "input", "reference_var_id": "15994664637690", "reference_layer_id": "1599466463769", "isDefault": true}}, "outputs": {"15994665258780": {"name": "output", "reference_var": "output"}}, "forward_connections": [{"src_var": "output", "dst_id": "1599466492197", "dst_var": "input"}], "backward_connections": [{"src_id": "1599466463769", "src_var": "output", "dst_var": "input"}], "previewVariable": "output", "previewVariableList": []}, "1599466570500": {"layerId": "1599466570500", "copyId": null, "copyContainerElement": null, "layerName": "Convolution_2", "layerType": "Other", "layerSettings": {"Conv_dim": "2D", "Patch_size": "3", "Stride": "1", "Padding": "SAME", "Feature_maps": "64", "Activation_function": "ReLU", "Dropout": false, "Keep_prob": "1", "Batch_norm": true, "PoolBool": false, "Pooling": "Max", "Pool_area": "2", "Pool_padding": "SAME", "Pool_stride": "2"}, "layerSettingsTabName": "Settings", "layerCode": null, "layerCodeError": null, "layerNone": false, "layerMeta": {"isInvisible": false, "isLock": false, "isSelected": false, "position": {"top": 180, "left": 255}, "OutputDim": "32x32x64", "InputDim": "[32, 32, 64]", "layerContainerName": "", "layerBgColor": "", "containerDiff": {"top": 0, "left": 0}}, "chartData": {}, "checkpoint": [], "endPoints": [], "componentName": "DeepLearningConv", "connectionOut": [], "connectionIn": [], "connectionArrow": [], "visited": true, "inputs": {"15994665705000": {"name": "input", "reference_var_id": "15994664921970", "reference_layer_id": "1599466492197", "isDefault": true}}, "outputs": {"15994665705010": {"name": "output", "reference_var": "output"}}, "forward_connections": [{"src_var": "output", "dst_id": "1599466592651", "dst_var": "input2"}], "backward_connections": [{"src_id": "1599466492197", "src_var": "output", "dst_var": "input"}], "previewVariable": "output", "previewVariableList": []}, "1599466592651": {"layerId": "1599466592651", "copyId": null, "copyContainerElement": null, "layerName": "Merge_1", "layerType": "Other", "layerSettings": {"Type": "Add", "Merge_dim": "-1"}, "layerSettingsTabName": "Settings", "layerCode": null, "layerCodeError": null, "layerNone": false, "layerMeta": {"isInvisible": false, "isLock": false, "isSelected": false, "position": {"top": 105, "left": 374.99999999999994}, "OutputDim": "32x32x64", "InputDim": "[[32, 32, 64], [32, 32, 64]]", "layerContainerName": "", "layerBgColor": "", "containerDiff": {"top": 0, "left": 0}}, "chartData": {}, "checkpoint": [], "endPoints": [], "componentName": "MathMerge", "connectionOut": [], "connectionIn": [], "connectionArrow": [], "visited": true, "inputs": {"15994665926510": {"name": "input1", "reference_var_id": "15994664921970", "reference_layer_id": "1599466492197", "isDefault": true}, "15994665926511": {"name": "input2", "reference_var_id": "15994665705010", "reference_layer_id": "1599466570500", "isDefault": true}}, "outputs": {"15994665926510": {"name": "output", "reference_var": "output"}}, "forward_connections": [{"src_var": "output", "dst_id": "1599466651057", "dst_var": "input"}], "backward_connections": [{"src_id": "1599466492197", "src_var": "output", "dst_var": "input1"}, {"src_id": "1599466570500", "src_var": "output", "dst_var": "input2"}], "previewVariable": "output", "previewVariableList": []}, "1599466651057": {"layerId": "1599466651057", "copyId": null, "copyContainerElement": null, "layerName": "Convolution_3", "layerType": "Other", "layerSettings": {"Conv_dim": "2D", "Patch_size": "3", "Stride": "2", "Padding": "SAME", "Feature_maps": "128", "Activation_function": "ReLU", "Dropout": false, "Keep_prob": "1", "Batch_norm": true, "PoolBool": false, "Pooling": "Max", "Pool_area": "2", "Pool_padding": "SAME", "Pool_stride": "2"}, "layerSettingsTabName": "Settings", "layerCode": null, "layerCodeError": null, "layerNone": false, "layerMeta": {"isInvisible": false, "isLock": false, "isSelected": false, "position": {"top": 15, "left": 495}, "OutputDim": "16x16x128", "InputDim": "[32, 32, 64]", "layerContainerName": "", "layerBgColor": "", "containerDiff": {"top": 0, "left": 0}}, "chartData": {}, "checkpoint": [], "endPoints": [], "componentName": "DeepLearningConv", "connectionOut": [], "connectionIn": [], "connectionArrow": [], "visited": true, "inputs": {"15994666510570": {"name": "input", "reference_var_id": "15994665926510", "reference_layer_id": "1599466592651", "isDefault": true}}, "outputs": {"15994666510570": {"name": "output", "reference_var": "output"}}, "forward_connections": [{"src_var": "output", "dst_id": "1599466690366", "dst_var": "input"}, {"src_var": "output", "dst_id": "1599466719000", "dst_var": "input1"}], "backward_connections": [{"src_id": "1599466592651", "src_var": "output", "dst_var": "input"}], "previewVariable": "output", "previewVariableList": []}, "1599466690366": {"layerId": "1599466690366", "copyId": null, "copyContainerElement": null, "layerName": "Convolution_4", "layerType": "Other", "layerSettings": {"Conv_dim": "2D", "Patch_size": "3", "Stride": "1", "Padding": "SAME", "Feature_maps": "128", "Activation_function": "ReLU", "Dropout": false, "Keep_prob": "1", "Batch_norm": true, "PoolBool": false, "Pooling": "Max", "Pool_area": "2", "Pool_padding": "SAME", "Pool_stride": "2"}, "layerSettingsTabName": "Settings", "layerCode": null, "layerCodeError": null, "layerNone": false, "layerMeta": {"isInvisible": false, "isLock": false, "isSelected": false, "position": {"top": 180, "left": 495}, "OutputDim": "16x16x128", "InputDim": "[16, 16, 128]", "layerContainerName": "", "layerBgColor": "", "containerDiff": {"top": 0, "left": 0}}, "chartData": {}, "checkpoint": [], "endPoints": [], "componentName": "DeepLearningConv", "connectionOut": [], "connectionIn": [], "connectionArrow": [], "visited": true, "inputs": {"15994666903670": {"name": "input", "reference_var_id": "15994666510570", "reference_layer_id": "1599466651057", "isDefault": true}}, "outputs": {"15994666903670": {"name": "output", "reference_var": "output"}}, "forward_connections": [{"src_var": "output", "dst_id": "1599466719000", "dst_var": "input2"}], "backward_connections": [{"src_id": "1599466651057", "src_var": "output", "dst_var": "input"}], "previewVariable": "output", "previewVariableList": []}, "1599466719000": {"layerId": "1599466719000", "copyId": null, "copyContainerElement": null, "layerName": "Merge_2", "layerType": "Other", "layerSettings": {"Type": "Add", "Merge_dim": "-1"}, "layerSettingsTabName": "Settings", "layerCode": null, "layerCodeError": null, "layerNone": false, "layerMeta": {"isInvisible": false, "isLock": false, "isSelected": false, "position": {"top": 105, "left": 614.9999999999999}, "OutputDim": "16x16x128", "InputDim": "[[16, 16, 128], [16, 16, 128]]", "layerContainerName": "", "layerBgColor": "", "containerDiff": {"top": 0, "left": 0}}, "chartData": {}, "checkpoint": [], "endPoints": [], "componentName": "MathMerge", "connectionOut": [], "connectionIn": [], "connectionArrow": [], "visited": false, "inputs": {"15994667190000": {"name": "input1", "reference_var_id": "15994666510570", "reference_layer_id": "1599466651057", "isDefault": true}, "15994667190001": {"name": "input2", "reference_var_id": "15994666903670", "reference_layer_id": "1599466690366", "isDefault": true}}, "outputs": {"15994667190000": {"name": "output", "reference_var": "output"}}, "forward_connections": [{"src_var": "output", "dst_id": "1599466746218", "dst_var": "input"}], "backward_connections": [{"src_id": "1599466651057", "src_var": "output", "dst_var": "input1"}, {"src_id": "1599466690366", "src_var": "output", "dst_var": "input2"}], "previewVariable": "output", "previewVariableList": []}, "1599466746218": {"layerId": "1599466746218", "copyId": null, "copyContainerElement": null, "layerName": "Convolution_5", "layerType": "Other", "layerSettings": {"Conv_dim": "2D", "Patch_size": "3", "Stride": "2", "Padding": "SAME", "Feature_maps": "256", "Activation_function": "ReLU", "Dropout": false, "Keep_prob": "1", "Batch_norm": true, "PoolBool": false, "Pooling": "Max", "Pool_area": "2", "Pool_padding": "SAME", "Pool_stride": "2"}, "layerSettingsTabName": "Settings", "layerCode": null, "layerCodeError": null, "layerNone": false, "layerMeta": {"isInvisible": false, "isLock": false, "isSelected": false, "position": {"top": 15, "left": 735.0000000000001}, "OutputDim": "8x8x256", "InputDim": "[16, 16, 128]", "layerContainerName": "", "layerBgColor": "", "containerDiff": {"top": 0, "left": 0}}, "chartData": {}, "checkpoint": [], "endPoints": [], "componentName": "DeepLearningConv", "connectionOut": [], "connectionIn": [], "connectionArrow": [], "visited": true, "inputs": {"15994667462190": {"name": "input", "reference_var_id": "15994667190000", "reference_layer_id": "1599466719000", "isDefault": true}}, "outputs": {"15994667462190": {"name": "output", "reference_var": "output"}}, "forward_connections": [{"src_var": "output", "dst_id": "1599466769589", "dst_var": "input"}, {"src_var": "output", "dst_id": "1599466798239", "dst_var": "input1"}], "backward_connections": [{"src_id": "1599466719000", "src_var": "output", "dst_var": "input"}], "previewVariable": "output", "previewVariableList": ["output", "W", "b"]}, "1599466769589": {"layerId": "1599466769589", "copyId": null, "copyContainerElement": null, "layerName": "Convolution_6", "layerType": "Other", "layerSettings": {"Conv_dim": "2D", "Patch_size": "3", "Stride": "1", "Padding": "SAME", "Feature_maps": "256", "Activation_function": "ReLU", "Dropout": false, "Keep_prob": "1", "Batch_norm": true, "PoolBool": false, "Pooling": "Max", "Pool_area": "2", "Pool_padding": "SAME", "Pool_stride": "2"}, "layerSettingsTabName": "Settings", "layerCode": null, "layerCodeError": null, "layerNone": false, "layerMeta": {"isInvisible": false, "isLock": false, "isSelected": false, "position": {"top": 180, "left": 735.0000000000001}, "OutputDim": "8x8x256", "InputDim": "[8, 8, 256]", "layerContainerName": "", "layerBgColor": "", "containerDiff": {"top": 0, "left": 0}}, "chartData": {}, "checkpoint": [], "endPoints": [], "componentName": "DeepLearningConv", "connectionOut": [], "connectionIn": [], "connectionArrow": [], "visited": true, "inputs": {"15994667695890": {"name": "input", "reference_var_id": "15994667462190", "reference_layer_id": "1599466746218", "isDefault": true}}, "outputs": {"15994667695890": {"name": "output", "reference_var": "output"}}, "forward_connections": [{"src_var": "output", "dst_id": "1599466798239", "dst_var": "input2"}], "backward_connections": [{"src_id": "1599466746218", "src_var": "output", "dst_var": "input"}], "previewVariable": "output", "previewVariableList": []}, "1599466798239": {"layerId": "1599466798239", "copyId": null, "copyContainerElement": null, "layerName": "Merge_3", "layerType": "Other", "layerSettings": {"Type": "Add", "Merge_dim": "-1"}, "layerSettingsTabName": "Settings", "layerCode": null, "layerCodeError": null, "layerNone": false, "layerMeta": {"isInvisible": false, "isLock": false, "isSelected": false, "position": {"top": 105, "left": 870}, "OutputDim": "8x8x256", "InputDim": "[[8, 8, 256], [8, 8, 256]]", "layerContainerName": "", "layerBgColor": "", "containerDiff": {"top": 0, "left": 0}}, "chartData": {}, "checkpoint": [], "endPoints": [], "componentName": "MathMerge", "connectionOut": [], "connectionIn": [], "connectionArrow": [], "visited": false, "inputs": {"15994667982390": {"name": "input1", "reference_var_id": "15994667462190", "reference_layer_id": "1599466746218", "isDefault": true}, "15994667982391": {"name": "input2", "reference_var_id": "15994667695890", "reference_layer_id": "1599466769589", "isDefault": true}}, "outputs": {"15994667982390": {"name": "output", "reference_var": "output"}}, "forward_connections": [{"src_var": "output", "dst_id": "1599466932842", "dst_var": "input"}], "backward_connections": [{"src_id": "1599466746218", "src_var": "output", "dst_var": "input1"}, {"src_id": "1599466769589", "src_var": "output", "dst_var": "input2"}], "previewVariable": "output", "previewVariableList": []}, "1599466932842": {"layerId": "1599466932842", "copyId": null, "copyContainerElement": null, "layerName": "Convolution_7", "layerType": "Other", "layerSettings": {"Conv_dim": "2D", "Patch_size": "3", "Stride": "9", "Padding": "SAME", "Feature_maps": "512", "Activation_function": "ReLU", "Dropout": false, "Keep_prob": "1", "Batch_norm": true, "PoolBool": false, "Pooling": "Max", "Pool_area": "2", "Pool_padding": "SAME", "Pool_stride": "2"}, "layerSettingsTabName": "Settings", "layerCode": null, "layerCodeError": null, "layerNone": false, "layerMeta": {"isInvisible": false, "isLock": false, "isSelected": false, "position": {"top": 105, "left": 990}, "OutputDim": "1x1x512", "InputDim": "", "layerContainerName": "", "layerBgColor": "", "containerDiff": {"top": 0, "left": 0}}, "chartData": {}, "checkpoint": [], "endPoints": [], "componentName": "DeepLearningConv", "connectionOut": [], "connectionIn": [], "connectionArrow": [], "visited": true, "inputs": {"15994669328430": {"name": "input", "reference_var_id": "15994667982390", "reference_layer_id": "1599466798239", "isDefault": true}}, "outputs": {"15994669328430": {"name": "output", "reference_var": "output"}}, "forward_connections": [{"src_var": "output", "dst_id": "1599467026932", "dst_var": "input"}], "backward_connections": [{"src_id": "1599466798239", "src_var": "output", "dst_var": "input"}], "previewVariable": "output", "previewVariableList": []}, "1599467026932": {"layerId": "1599467026932", "copyId": null, "copyContainerElement": null, "layerName": "Fully Connected_1", "layerType": "Other", "layerSettings": {"Neurons": "6", "Activation_function": "Softmax", "Dropout": false, "Keep_prob": "1", "Batch_norm": true}, "layerSettingsTabName": "Settings", "layerCode": null, "layerCodeError": null, "layerNone": false, "layerMeta": {"isInvisible": false, "isLock": false, "isSelected": false, "position": {"top": 105, "left": 1110}, "OutputDim": "6", "InputDim": "", "layerContainerName": "", "layerBgColor": "", "containerDiff": {"top": 0, "left": 0}}, "chartData": {}, "checkpoint": [], "endPoints": [], "componentName": "DeepLearningFC", "connectionOut": [], "connectionIn": [], "connectionArrow": [], "visited": true, "inputs": {"15994670269330": {"name": "input", "reference_var_id": "15994669328430", "reference_layer_id": "1599466932842", "isDefault": true}}, "outputs": {"15994670269330": {"name": "output", "reference_var": "output"}}, "forward_connections": [{"src_var": "output", "dst_id": "1599467087463", "dst_var": "predictions"}], "backward_connections": [{"src_id": "1599466932842", "src_var": "output", "dst_var": "input"}], "previewVariable": "output", "previewVariableList": []}, "1599467087463": {"layerId": "1599467087463", "copyId": null, "copyContainerElement": null, "layerName": "Normal_1", "layerType": "Training", "layerSettings": {"Labels": "", "Epochs": "10", "N_class": "1", "Loss": "Cross_entropy", "Stop_condition": "Epochs", "Stop_Target_Accuracy": "0", "Class_weights": "1", "Learning_rate": "0.001", "Optimizer": "ADAM", "Beta_1": "0.9", "Beta_2": "0.999", "Momentum": "0.9", "Decay_steps": "100000", "Decay_rate": "0.96", "Training_iters": "20000", "Batch_size": "256"}, "layerSettingsTabName": "Settings", "layerCode": null, "layerCodeError": null, "layerNone": false, "layerMeta": {"isInvisible": false, "isLock": false, "isSelected": true, "position": {"top": 320, "left": 1100}, "OutputDim": "", "InputDim": "", "layerContainerName": "", "layerBgColor": "", "containerDiff": {"top": 0, "left": 0}}, "chartData": {}, "checkpoint": [], "endPoints": [], "componentName": "TrainNormal", "connectionOut": [], "connectionIn": [], "connectionArrow": [], "visited": true, "inputs": {"15994670874630": {"name": "predictions", "reference_var_id": "15994670269330", "reference_layer_id": "1599467026932", "isDefault": true}, "15994670874631": {"name": "labels", "reference_var_id": "15994671453890", "reference_layer_id": "1599467145388", "isDefault": true}}, "outputs": {}, "forward_connections": [], "backward_connections": [{"src_id": "1599467026932", "src_var": "output", "dst_var": "predictions"}, {"src_id": "1599467145388", "src_var": "output", "dst_var": "labels"}], "previewVariable": "output", "previewVariableList": []}, "1599467145388": {"layerId": "1599467145388", "copyId": null, "copyContainerElement": null, "layerName": "OneHot_1", "layerType": "Other", "layerSettings": {"N_class": "6"}, "layerSettingsTabName": "Settings", "layerCode": null, "layerCodeError": null, "layerNone": false, "layerMeta": {"isInvisible": false, "isLock": false, "isSelected": false, "position": {"top": 340, "left": 140}, "OutputDim": "6", "InputDim": "", "layerContainerName": "", "layerBgColor": "", "containerDiff": {"top": 0, "left": 0}}, "chartData": {}, "checkpoint": [], "endPoints": [], "componentName": "ProcessOneHot", "connectionOut": [], "connectionIn": [], "connectionArrow": [], "visited": true, "inputs": {"15994671453890": {"name": "input", "reference_var_id": "15994664752390", "reference_layer_id": "1599466475239", "isDefault": true}}, "outputs": {"15994671453890": {"name": "output", "reference_var": "output"}}, "forward_connections": [{"src_var": "output", "dst_id": "1599467087463", "dst_var": "labels"}], "backward_connections": [{"src_id": "1599466475239", "src_var": "output", "dst_var": "input"}], "previewVariable": "output", "previewVariableList": []}}, "networkRootFolder": "C:\\Users\\ARUNESH\\Documents\\Perceptilabs\\Default/Textile_1", "apiMeta": {"model_id": 52, "project": 1, "name": "Textile_1", "created": "2020-09-07T08:14:18.944246Z", "updated": "2020-09-07T08:29:59.282712Z", "saved_by": "", "location": "C:\\Users\\ARUNESH\\Documents\\Perceptilabs\\Default/Textile_1", "saved_version_location": ""}}